OmerAPI/Apihelpers.py
OmerAPI/BinanceTrRequests.py
OmerAPI/BinanceTrService.py
OmerAPI/TimeModel.py
OmerAPI/UserModel.py
OmerAPI/__init__.py
OmerAPI/config.py
OmerAPI/constants.json
OmerAPI-2.0.dist-info/LICENSE
OmerAPI-2.0.dist-info/METADATA
OmerAPI-2.0.dist-info/WHEEL
OmerAPI-2.0.dist-info/top_level.txt
OmerAPI-2.0.dist-info/RECORD
