Metadata-Version: 2.1
Name: OmerAPI
Version: 2.0
Summary: TRbinance API implementation in python.
Home-page: UNKNOWN
Author: Omer Cerrahpasa
Author-email: omer.cp61@gmail.com
License: UNKNOWN
Platform: UNKNOWN
Classifier: Programming Language :: Python :: 3
Classifier: License :: OSI Approved :: MIT License
Classifier: Operating System :: OS Independent
Requires-Python: >=3.6
License-File: LICENSE
